<?xml version="1.0" encoding="UTF-8"?>
<Scores><HighScore><Score>100</Score><EncryptedData Type="http://www.w3.org/2001/04/xmlenc#Element" xmlns="http://www.w3.org/2001/04/xmlenc#"><EncryptionMethod Algorithm="http://www.w3.org/2001/04/xmlenc#aes256-cbc" /><KeyInfo xmlns="http://www.w3.org/2000/09/xmldsig#"><EncryptedKey xmlns="http://www.w3.org/2001/04/xmlenc#"><EncryptionMethod Algorithm="http://www.w3.org/2001/04/xmlenc#rsa-1_5" /><KeyInfo xmlns="http://www.w3.org/2000/09/xmldsig#"><KeyName>rsaKey</KeyName></KeyInfo><CipherData><CipherValue>enzDxkHIB9s0qrCr0YQX8fh6sSa/lXfCX/ol3IbffFIcJuioY5N7YqEZ/PsexmFAoSJHnVZIpztfLv7LQ3Xho6xRmRGUMkJJa2QsvxDZqzdrCf5zyg5Of2g+FbINDJBTkc7vlhYH+Y6x9yTqb1ncMOR5XT9yoDdlwwC24pJDUEA=</CipherValue></CipherData></EncryptedKey></KeyInfo><CipherData><CipherValue>rrx373q/foihzMbqC/ZJxS7hm6BWCOQ5vTNh9hmmtKfkd3ngP9Guzg42RZBsjKLd</CipherValue></CipherData></EncryptedData><Date>22/03/2013 22:13:17</Date></HighScore></Scores>